analog-digital-chip-design-eda/labs/eda/aimc-multi-clock-control-subsystem-openlane-prep/src/aimc_tile_readout.v
module aimc_tile_readout (
    input wire clk,
    input wire rst_n,
    input wire sample_valid,
    input wire tile_enabled,
    input wire [11:0] adc_code,
    input wire signed [8:0] zero_code,
    input wire signed [8:0] gain_q6,
    input wire signed [15:0] bias,
    input wire [9:0] residual_abs,
    input wire [9:0] residual_budget,
    input wire [15:0] calibration_age,
    output reg signed [15:0] corrected_value,
    output reg output_valid,
    output reg fallback,
    output reg [3:0] reason
);
    localparam REASON_OK = 4'd0;
    localparam REASON_TILE_DISABLED = 4'd1;
    localparam REASON_RESIDUAL_HIGH = 4'd2;
    localparam REASON_CALIBRATION_STALE = 4'd3;
    localparam REASON_SATURATED_HIGH = 4'd4;
    localparam REASON_SATURATED_LOW = 4'd5;

    localparam [15:0] MAX_CALIBRATION_AGE = 16'd1024;

    wire signed [15:0] centered_adc = $signed({4'b0000, adc_code}) - {{7{zero_code[8]}}, zero_code};
    wire signed [25:0] scaled = centered_adc * gain_q6;
    wire signed [25:0] corrected_wide = $signed(scaled >>> 6) + {{10{bias[15]}}, bias};

    wire saturated_high = corrected_wide > 26'sd2047;
    wire saturated_low = corrected_wide < -26'sd2048;
    wire residual_high = residual_abs > residual_budget;
    wire calibration_stale = calibration_age >= MAX_CALIBRATION_AGE;
    wire should_fallback = (!tile_enabled) || residual_high || calibration_stale || saturated_high || saturated_low;

    always @(posedge clk or negedge rst_n) begin
        if (!rst_n) begin
            corrected_value <= 16'sd0;
            output_valid <= 1'b0;
            fallback <= 1'b0;
            reason <= REASON_OK;
        end else begin
            output_valid <= 1'b0;
            fallback <= 1'b0;
            reason <= REASON_OK;

            if (sample_valid) begin
                output_valid <= !should_fallback;
                fallback <= should_fallback;

                if (saturated_high) begin
                    corrected_value <= 16'sd2047;
                    reason <= REASON_SATURATED_HIGH;
                end else if (saturated_low) begin
                    corrected_value <= -16'sd2048;
                    reason <= REASON_SATURATED_LOW;
                end else begin
                    corrected_value <= corrected_wide[15:0];
                    if (!tile_enabled) begin
                        reason <= REASON_TILE_DISABLED;
                    end else if (residual_high) begin
                        reason <= REASON_RESIDUAL_HIGH;
                    end else if (calibration_stale) begin
                        reason <= REASON_CALIBRATION_STALE;
                    end else begin
                        reason <= REASON_OK;
                    end
                end
            end
        end
    end
endmodule

analog-digital-chip-design-eda/labs/digital/aimc-control-plane-rtl/aimc_tile_readout_tb.v
`timescale 1ns/1ps

module aimc_tile_readout_tb;
    reg clk = 0;
    reg rst_n = 0;
    reg sample_valid = 0;
    reg tile_enabled = 1;
    reg [11:0] adc_code = 12'd0;
    reg signed [8:0] zero_code = 9'sd128;
    reg signed [8:0] gain_q6 = 9'sd64;
    reg signed [15:0] bias = 16'sd0;
    reg [9:0] residual_abs = 10'd0;
    reg [9:0] residual_budget = 10'd20;
    reg [15:0] calibration_age = 16'd0;
    wire signed [15:0] corrected_value;
    wire output_valid;
    wire fallback;
    wire [3:0] reason;

    aimc_tile_readout dut (
        .clk(clk),
        .rst_n(rst_n),
        .sample_valid(sample_valid),
        .tile_enabled(tile_enabled),
        .adc_code(adc_code),
        .zero_code(zero_code),
        .gain_q6(gain_q6),
        .bias(bias),
        .residual_abs(residual_abs),
        .residual_budget(residual_budget),
        .calibration_age(calibration_age),
        .corrected_value(corrected_value),
        .output_valid(output_valid),
        .fallback(fallback),
        .reason(reason)
    );

    always #5 clk = ~clk;

    task run_sample;
        input [160*8:1] name;
        input in_tile_enabled;
        input [11:0] in_adc_code;
        input signed [8:0] in_zero_code;
        input signed [8:0] in_gain_q6;
        input signed [15:0] in_bias;
        input [9:0] in_residual_abs;
        input [15:0] in_calibration_age;
        input signed [15:0] expected_value;
        input expected_valid;
        input expected_fallback;
        input [3:0] expected_reason;
        begin
            @(negedge clk);
            tile_enabled = in_tile_enabled;
            adc_code = in_adc_code;
            zero_code = in_zero_code;
            gain_q6 = in_gain_q6;
            bias = in_bias;
            residual_abs = in_residual_abs;
            calibration_age = in_calibration_age;
            sample_valid = 1'b1;
            @(negedge clk);
            sample_valid = 1'b0;
            #1;
            $display("%0s,value=%0d,valid=%0d,fallback=%0d,reason=%0d",
                name, corrected_value, output_valid, fallback, reason);
            if (corrected_value !== expected_value ||
                output_valid !== expected_valid ||
                fallback !== expected_fallback ||
                reason !== expected_reason) begin
                $display("FAIL %0s expected value=%0d valid=%0d fallback=%0d reason=%0d",
                    name, expected_value, expected_valid, expected_fallback, expected_reason);
                $finish;
            end
        end
    endtask

    initial begin
        $dumpfile("aimc_tile_readout.vcd");
        $dumpvars(0, aimc_tile_readout_tb);

        repeat (2) @(negedge clk);
        rst_n = 1'b1;

        run_sample("centered_adc_with_unit_gain", 1'b1, 12'd160, 9'sd128, 9'sd64, 16'sd0, 10'd3, 16'd32, 16'sd32, 1'b1, 1'b0, 4'd0);
        run_sample("gain_and_bias_correction", 1'b1, 12'd160, 9'sd128, 9'sd96, -16'sd5, 10'd3, 16'd32, 16'sd43, 1'b1, 1'b0, 4'd0);
        run_sample("disabled_tile_fallback", 1'b0, 12'd160, 9'sd128, 9'sd64, 16'sd0, 10'd3, 16'd32, 16'sd32, 1'b0, 1'b1, 4'd1);
        run_sample("residual_fallback", 1'b1, 12'd160, 9'sd128, 9'sd64, 16'sd0, 10'd40, 16'd32, 16'sd32, 1'b0, 1'b1, 4'd2);
        run_sample("stale_calibration_fallback", 1'b1, 12'd160, 9'sd128, 9'sd64, 16'sd0, 10'd3, 16'd2048, 16'sd32, 1'b0, 1'b1, 4'd3);
        run_sample("high_saturation_fallback", 1'b1, 12'd4095, 9'sd0, 9'sd64, 16'sd0, 10'd3, 16'd32, 16'sd2047, 1'b0, 1'b1, 4'd4);
        run_sample("low_saturation_fallback", 1'b1, 12'd0, 9'sd255, 9'sd64, -16'sd2000, 10'd3, 16'd32, -16'sd2048, 1'b0, 1'b1, 4'd5);

        $display("PASS aimc_tile_readout_tb");
        $finish;
    end
endmodule

analog-digital-chip-design-eda/labs/digital/aimc-control-plane-rtl/aimc_tile_readout.vcd
$date
	Sat Aug 29 05:37:55 2026
$end
$version
	Icarus Verilog
$end
$timescale
	1ps
$end
$scope module aimc_tile_readout_tb $end
$var wire 4 ! reason [3:0] $end
$var wire 1 " output_valid $end
$var wire 1 # fallback $end
$var wire 16 $ corrected_value [15:0] $end
$var reg 12 % adc_code [11:0] $end
$var reg 16 & bias [15:0] $end
$var reg 16 ' calibration_age [15:0] $end
$var reg 1 ( clk $end
$var reg 9 ) gain_q6 [8:0] $end
$var reg 10 * residual_abs [9:0] $end
$var reg 10 + residual_budget [9:0] $end
$var reg 1 , rst_n $end
$var reg 1 - sample_valid $end
$var reg 1 . tile_enabled $end
$var reg 9 / zero_code [8:0] $end
$scope module dut $end
$var wire 12 0 adc_code [11:0] $end
$var wire 16 1 bias [15:0] $end
$var wire 16 2 calibration_age [15:0] $end
$var wire 1 ( clk $end
$var wire 9 3 gain_q6 [8:0] $end
$var wire 10 4 residual_abs [9:0] $end
$var wire 10 5 residual_budget [9:0] $end
$var wire 1 , rst_n $end
$var wire 1 - sample_valid $end
$var wire 1 6 should_fallback $end
$var wire 1 . tile_enabled $end
$var wire 9 7 zero_code [8:0] $end
$var wire 26 8 scaled [25:0] $end
$var wire 1 9 saturated_low $end
$var wire 1 : saturated_high $end
$var wire 1 ; residual_high $end
$var wire 26 < corrected_wide [25:0] $end
$var wire 16 = centered_adc [15:0] $end
$var wire 1 > calibration_stale $end
$var reg 16 ? corrected_value [15:0] $end
$var reg 1 # fallback $end
$var reg 1 " output_valid $end
$var reg 4 @ reason [3:0] $end
$upscope $end
$scope task run_sample $end
$var reg 1 A expected_fallback $end
$var reg 4 B expected_reason [3:0] $end
$var reg 1 C expected_valid $end
$var reg 16 D expected_value [15:0] $end
$var reg 12 E in_adc_code [11:0] $end
$var reg 16 F in_bias [15:0] $end
$var reg 16 G in_calibration_age [15:0] $end
$var reg 9 H in_gain_q6 [8:0] $end
$var reg 10 I in_residual_abs [9:0] $end
$var reg 1 J in_tile_enabled $end
$var reg 9 K in_zero_code [8:0] $end
$var reg 1280 L name [1280:1] $end
$upscope $end
$upscope $end
$enddefinitions $end
#0
$dumpvars
bx L
bx K
xJ
bx I
bx H
bx G
bx F
bx E
bx D
xC
bx B
xA
b0 @
b0 ?
0>
b1111111110000000 =
b11111111111111111110000000 <
0;
0:
09
b11111111111110000000000000 8
b10000000 7
06
b10100 5
b0 4
b1000000 3
b0 2
b0 1
b0 0
b10000000 /
1.
0-
0,
b10100 +
b0 *
b1000000 )
0(
b0 '
b0 &
b0 %
b0 $
0#
0"
b0 !
$end
#5000
1(
#10000
0(
#15000
1(
#20000
b0 B
0A
1C
b100000 D
b100000 G
b11 I
b0 F
b1000000 H
b10000000 K
b10100000 E
1J
b11000110110010101101110011101000110010101110010011001010110010001011111011000010110010001100011010111110111011101101001011101000110100001011111011101010110111001101001011101000101111101100111011000010110100101101110 L
1,
0(
#25000
1(
#30000
b100000 <
1-
b100000 '
b100000 2
b11 *
b11 4
b100000000000 8
b100000 =
b10100000 %
b10100000 0
0(
#35000
b100000 $
b100000 ?
1"
1(
#40000
0-
0(
#41000
b101011 D
b1111111111111011 F
b1100000 H
b11001110110000101101001011011100101111101100001011011100110010001011111011000100110100101100001011100110101111101100011011011110111001001110010011001010110001101110100011010010110111101101110 L
#45000
0"
1(
#50000
06
09
1-
0:
b101011 <
b1111111111111011 &
b1111111111111011 1
b110000000000 8
b1100000 )
b1100000 3
0(
#55000
b101011 $
b101011 ?
1"
1(
#60000
0-
0(
#61000
b1 B
1A
0C
b100000 D
b0 F
b1000000 H
0J
b1100100011010010111001101100001011000100110110001100101011001000101111101110100011010010110110001100101010111110110011001100001011011000110110001100010011000010110001101101011 L
#65000
0"
1(
#70000
0:
16
1-
09
b100000 <
b0 &
b0 1
b100000000000 8
b1000000 )
b1000000 3
0.
0(
#75000
b1 !
b1 @
b100000 $
b100000 ?
1#
1(
#80000
0-
0(
#81000
b10 B
b101000 I
1J
b111001001100101011100110110100101100100011101010110000101101100010111110110011001100001011011000110110001100010011000010110001101101011 L
#85000
b0 !
b0 @
0#
1(
#90000
1-
1;
b101000 *
b101000 4
1.
0(
#95000
b10 !
b10 @
1#
1(
#100000
0-
0(
#101000
b11 B
b100000000000 G
b11 I
b111001101110100011000010110110001100101010111110110001101100001011011000110100101100010011100100110000101110100011010010110111101101110010111110110011001100001011011000110110001100010011000010110001101101011 L
#105000
b0 !
b0 @
0#
1(
#110000
1-
1>
b100000000000 '
b100000000000 2
0;
b11 *
b11 4
0(
#115000
b11 !
b11 @
1#
1(
#120000
0-
0(
#121000
b100 B
b11111111111 D
b100000 G
b0 K
b111111111111 E
b11010000110100101100111011010000101111101110011011000010111010001110101011100100110000101110100011010010110111101101110010111110110011001100001011011000110110001100010011000010110001101101011 L
#125000
b0 !
b0 @
0#
1(
#130000
1:
b111111111111 <
1-
0>
b100000 '
b100000 2
b0 /
b0 7
b111111111111000000 8
b111111111111 =
b111111111111 %
b111111111111 0
0(
#135000
b100 !
b100 @
b11111111111 $
b11111111111 ?
1#
1(
#140000
0-
0(
#141000
b101 B
b1111100000000000 D
b1111100000110000 F
b11111111 K
b0 E
b110110001101111011101110101111101110011011000010111010001110101011100100110000101110100011010010110111101101110010111110110011001100001011011000110110001100010011000010110001101101011 L
#145000
b0 !
b0 @
0#
1(
#150000
0:
19
1-
b11111111111111011100110001 <
b1111100000110000 &
b1111100000110000 1
b11111111 /
b11111111 7
b11111111111100000001000000 8
b1111111100000001 =
b0 %
b0 0
0(
#155000
b101 !
b101 @
b1111100000000000 $
b1111100000000000 ?
1#
1(
#160000
0-
0(
