analog-digital-chip-design-eda/labs/digital/aimc-control-plane-rtl/generated_micro_tile_cases.vh
// Generated by labs/analog/analog-in-memory-foundation-model-hardware/python/generate_micro_tile_rtl_vectors.py
// Do not edit by hand; edit the analog vector generator instead.
        run_case("qkv_analog_readout_accepted", 4'd1, 1'b1, 8'd11, 1'b1, 10'd3, 16'd32, 2'd1, 4'd1, 8'd0, 16'd0, 16'd1, 16'd0, 16'd0, 2'd0);
        run_case("qkv_residual_forces_fallback", 4'd1, 1'b1, 8'd12, 1'b1, 10'd40, 16'd32, 2'd0, 4'd10, 8'd12, 16'd1, 16'd1, 16'd1, 16'd0, 2'd0);
        run_case("qkv_stale_calibration_fallback", 4'd1, 1'b1, 8'd17, 1'b1, 10'd3, 16'd2048, 2'd0, 4'd11, 8'd17, 16'd2, 16'd1, 16'd1, 16'd1, 2'd1);
        run_case("qkv_disabled_tile_fallback", 4'd1, 1'b1, 8'd13, 1'b0, 10'd3, 16'd32, 2'd0, 4'd9, 8'd13, 16'd3, 16'd1, 16'd1, 16'd1, 2'd1);
        run_case("attention_score_hybrid_review", 4'd2, 1'b1, 8'd14, 1'b1, 10'd3, 16'd32, 2'd2, 4'd2, 8'd13, 16'd3, 16'd1, 16'd1, 16'd1, 2'd1);
        run_case("softmax_partition_digital", 4'd4, 1'b1, 8'd15, 1'b1, 10'd3, 16'd32, 2'd0, 4'd0, 8'd13, 16'd3, 16'd1, 16'd1, 16'd1, 2'd1);
        run_case("missing_weights_partition_digital", 4'd1, 1'b0, 8'd16, 1'b1, 10'd3, 16'd32, 2'd0, 4'd3, 8'd13, 16'd3, 16'd1, 16'd1, 16'd1, 2'd1);
        run_case("second_residual_disables_tile", 4'd1, 1'b1, 8'd18, 1'b1, 10'd44, 16'd32, 2'd0, 4'd10, 8'd18, 16'd4, 16'd1, 16'd2, 16'd1, 2'd2);

analog-digital-chip-design-eda/labs/eda/aimc-multi-clock-control-subsystem-openlane-prep/src/aimc_tile_readout.v
module aimc_tile_readout (
    input wire clk,
    input wire rst_n,
    input wire sample_valid,
    input wire tile_enabled,
    input wire [11:0] adc_code,
    input wire signed [8:0] zero_code,
    input wire signed [8:0] gain_q6,
    input wire signed [15:0] bias,
    input wire [9:0] residual_abs,
    input wire [9:0] residual_budget,
    input wire [15:0] calibration_age,
    output reg signed [15:0] corrected_value,
    output reg output_valid,
    output reg fallback,
    output reg [3:0] reason
);
    localparam REASON_OK = 4'd0;
    localparam REASON_TILE_DISABLED = 4'd1;
    localparam REASON_RESIDUAL_HIGH = 4'd2;
    localparam REASON_CALIBRATION_STALE = 4'd3;
    localparam REASON_SATURATED_HIGH = 4'd4;
    localparam REASON_SATURATED_LOW = 4'd5;

    localparam [15:0] MAX_CALIBRATION_AGE = 16'd1024;

    wire signed [15:0] centered_adc = $signed({4'b0000, adc_code}) - {{7{zero_code[8]}}, zero_code};
    wire signed [25:0] scaled = centered_adc * gain_q6;
    wire signed [25:0] corrected_wide = $signed(scaled >>> 6) + {{10{bias[15]}}, bias};

    wire saturated_high = corrected_wide > 26'sd2047;
    wire saturated_low = corrected_wide < -26'sd2048;
    wire residual_high = residual_abs > residual_budget;
    wire calibration_stale = calibration_age >= MAX_CALIBRATION_AGE;
    wire should_fallback = (!tile_enabled) || residual_high || calibration_stale || saturated_high || saturated_low;

    always @(posedge clk or negedge rst_n) begin
        if (!rst_n) begin
            corrected_value <= 16'sd0;
            output_valid <= 1'b0;
            fallback <= 1'b0;
            reason <= REASON_OK;
        end else begin
            output_valid <= 1'b0;
            fallback <= 1'b0;
            reason <= REASON_OK;

            if (sample_valid) begin
                output_valid <= !should_fallback;
                fallback <= should_fallback;

                if (saturated_high) begin
                    corrected_value <= 16'sd2047;
                    reason <= REASON_SATURATED_HIGH;
                end else if (saturated_low) begin
                    corrected_value <= -16'sd2048;
                    reason <= REASON_SATURATED_LOW;
                end else begin
                    corrected_value <= corrected_wide[15:0];
                    if (!tile_enabled) begin
                        reason <= REASON_TILE_DISABLED;
                    end else if (residual_high) begin
                        reason <= REASON_RESIDUAL_HIGH;
                    end else if (calibration_stale) begin
                        reason <= REASON_CALIBRATION_STALE;
                    end else begin
                        reason <= REASON_OK;
                    end
                end
            end
        end
    end
endmodule

analog-digital-chip-design-eda/labs/eda/aimc-micro-tile-controller-openlane-prep/src/aimc_operation_partition.v
module aimc_operation_partition (
    input wire [3:0] op_class,
    input wire resident_weights,
    input wire [7:0] estimated_state_error,
    input wire [7:0] state_error_budget,
    input wire [7:0] attention_flip_rate,
    input wire [7:0] attention_flip_budget,
    input wire [7:0] token_flip_rate,
    input wire [7:0] token_flip_budget,
    input wire [15:0] calibration_age,
    input wire [7:0] weak_tiles,
    output reg [1:0] placement,
    output reg [3:0] reason
);
    localparam OP_EMBEDDING = 4'd0;
    localparam OP_QKV = 4'd1;
    localparam OP_ATTENTION_SCORE = 4'd2;
    localparam OP_MASK = 4'd3;
    localparam OP_SOFTMAX = 4'd4;
    localparam OP_VALUE_MIX = 4'd5;
    localparam OP_OUT_PROJ = 4'd6;
    localparam OP_MLP = 4'd7;
    localparam OP_RESIDUAL = 4'd8;
    localparam OP_NORM = 4'd9;
    localparam OP_KV_CACHE = 4'd10;
    localparam OP_LOGITS = 4'd11;
    localparam OP_SAMPLING = 4'd12;
    localparam OP_ADAPTER = 4'd13;

    localparam PLACE_DIGITAL = 2'd0;
    localparam PLACE_ANALOG = 2'd1;
    localparam PLACE_HYBRID = 2'd2;

    localparam REASON_DIGITAL_RULE = 4'd0;
    localparam REASON_FIXED_WEIGHT_ANALOG = 4'd1;
    localparam REASON_HYBRID_NEEDS_EVIDENCE = 4'd2;
    localparam REASON_MISSING_WEIGHTS = 4'd3;
    localparam REASON_STATE_ERROR_HIGH = 4'd4;
    localparam REASON_ATTENTION_SELECTION_HIGH = 4'd5;
    localparam REASON_TOKEN_CHOICE_HIGH = 4'd6;
    localparam REASON_STALE_WEAK_TILES = 4'd7;
    localparam REASON_UNKNOWN_OP = 4'd15;

    wire stale_weak_tiles = (calibration_age >= 16'd1024) && (weak_tiles >= 8'd4);
    wire fixed_weight_op = (op_class == OP_QKV) || (op_class == OP_OUT_PROJ) || (op_class == OP_MLP);
    wire hybrid_candidate = (op_class == OP_ATTENTION_SCORE) || (op_class == OP_VALUE_MIX) || (op_class == OP_LOGITS) || (op_class == OP_ADAPTER);
    wire digital_only = (op_class == OP_EMBEDDING) || (op_class == OP_MASK) || (op_class == OP_SOFTMAX) ||
        (op_class == OP_RESIDUAL) || (op_class == OP_NORM) || (op_class == OP_KV_CACHE) || (op_class == OP_SAMPLING);

    always @* begin
        placement = PLACE_DIGITAL;
        reason = REASON_UNKNOWN_OP;

        if (digital_only) begin
            placement = PLACE_DIGITAL;
            reason = REASON_DIGITAL_RULE;
        end else if (!resident_weights && (fixed_weight_op || hybrid_candidate)) begin
            placement = PLACE_DIGITAL;
            reason = REASON_MISSING_WEIGHTS;
        end else if (estimated_state_error > state_error_budget) begin
            placement = PLACE_DIGITAL;
            reason = REASON_STATE_ERROR_HIGH;
        end else if (stale_weak_tiles) begin
            placement = PLACE_DIGITAL;
            reason = REASON_STALE_WEAK_TILES;
        end else if ((op_class == OP_ATTENTION_SCORE || op_class == OP_VALUE_MIX) && (attention_flip_rate > attention_flip_budget)) begin
            placement = PLACE_DIGITAL;
            reason = REASON_ATTENTION_SELECTION_HIGH;
        end else if (op_class == OP_LOGITS && (token_flip_rate > token_flip_budget)) begin
            placement = PLACE_DIGITAL;
            reason = REASON_TOKEN_CHOICE_HIGH;
        end else if (fixed_weight_op) begin
            placement = PLACE_ANALOG;
            reason = REASON_FIXED_WEIGHT_ANALOG;
        end else if (hybrid_candidate) begin
            placement = PLACE_HYBRID;
            reason = REASON_HYBRID_NEEDS_EVIDENCE;
        end else begin
            placement = PLACE_DIGITAL;
            reason = REASON_UNKNOWN_OP;
        end
    end
endmodule

analog-digital-chip-design-eda/labs/digital/aimc-control-plane-rtl/aimc_micro_tile_controller.v
module aimc_micro_tile_controller (
    input wire clk,
    input wire rst_n,
    input wire sample_valid,
    input wire [3:0] op_class,
    input wire resident_weights,
    input wire [7:0] tile_id,
    input wire tile_enabled,
    input wire [11:0] adc_code,
    input wire signed [8:0] zero_code,
    input wire signed [8:0] gain_q6,
    input wire signed [15:0] bias,
    input wire [7:0] estimated_state_error,
    input wire [7:0] state_error_budget,
    input wire [7:0] attention_flip_rate,
    input wire [7:0] attention_flip_budget,
    input wire [7:0] token_flip_rate,
    input wire [7:0] token_flip_budget,
    input wire [9:0] residual_abs,
    input wire [9:0] residual_budget,
    input wire [15:0] calibration_age,
    input wire [7:0] weak_tiles,
    input wire calibration_done,
    input wire probe_request,
    input wire probe_passed,
    input wire probe_failed,
    output wire signed [15:0] corrected_value,
    output reg [1:0] execution_path,
    output reg [3:0] reason,
    output reg [7:0] last_fallback_tile_id,
    output reg [15:0] fallback_count,
    output reg [15:0] accepted_count,
    output reg [15:0] residual_fallback_count,
    output reg [15:0] stale_fallback_count,
    output reg [1:0] tile_health_action
);
    localparam PLACE_DIGITAL = 2'd0;
    localparam PLACE_ANALOG = 2'd1;
    localparam PLACE_HYBRID = 2'd2;

    localparam EXEC_DIGITAL = 2'd0;
    localparam EXEC_ANALOG_ACCEPTED = 2'd1;
    localparam EXEC_HYBRID_REVIEW = 2'd2;

    localparam REASON_PARTITION_DIGITAL = 4'd0;
    localparam REASON_ANALOG_ACCEPTED = 4'd1;
    localparam REASON_HYBRID_REVIEW = 4'd2;
    localparam REASON_TILE_READOUT_FALLBACK = 4'd8;
    localparam READOUT_REASON_RESIDUAL_HIGH = 4'd2;
    localparam READOUT_REASON_CALIBRATION_STALE = 4'd3;
    localparam TILE_SERVE = 2'd0;
    localparam TILE_RECALIBRATE = 2'd1;
    localparam TILE_DISABLE = 2'd2;
    localparam TILE_PROBE = 2'd3;

    wire [1:0] placement;
    wire [3:0] partition_reason;
    wire readout_valid;
    wire readout_fallback;
    wire [3:0] readout_reason;
    reg analog_read_pending;
    reg [7:0] pending_tile_id;

    aimc_operation_partition partition (
        .op_class(op_class),
        .resident_weights(resident_weights),
        .estimated_state_error(estimated_state_error),
        .state_error_budget(state_error_budget),
        .attention_flip_rate(attention_flip_rate),
        .attention_flip_budget(attention_flip_budget),
        .token_flip_rate(token_flip_rate),
        .token_flip_budget(token_flip_budget),
        .calibration_age(calibration_age),
        .weak_tiles(weak_tiles),
        .placement(placement),
        .reason(partition_reason)
    );

    aimc_tile_readout readout (
        .clk(clk),
        .rst_n(rst_n),
        .sample_valid(sample_valid && (placement == PLACE_ANALOG)),
        .tile_enabled(tile_enabled),
        .adc_code(adc_code),
        .zero_code(zero_code),
        .gain_q6(gain_q6),
        .bias(bias),
        .residual_abs(residual_abs),
        .residual_budget(residual_budget),
        .calibration_age(calibration_age),
        .corrected_value(corrected_value),
        .output_valid(readout_valid),
        .fallback(readout_fallback),
        .reason(readout_reason)
    );

    always @(posedge clk or negedge rst_n) begin
        if (!rst_n) begin
            execution_path <= EXEC_DIGITAL;
            reason <= REASON_PARTITION_DIGITAL;
            analog_read_pending <= 1'b0;
            pending_tile_id <= 8'd0;
            last_fallback_tile_id <= 8'd0;
            fallback_count <= 16'd0;
            accepted_count <= 16'd0;
            residual_fallback_count <= 16'd0;
            stale_fallback_count <= 16'd0;
            tile_health_action <= TILE_SERVE;
        end else if (tile_health_action == TILE_DISABLE && probe_request) begin
            tile_health_action <= TILE_PROBE;
        end else if (tile_health_action == TILE_PROBE && probe_passed) begin
            tile_health_action <= TILE_SERVE;
        end else if (tile_health_action == TILE_PROBE && probe_failed) begin
            tile_health_action <= TILE_DISABLE;
        end else if (tile_health_action == TILE_RECALIBRATE && calibration_done) begin
            tile_health_action <= TILE_SERVE;
        end else if (analog_read_pending) begin
            analog_read_pending <= 1'b0;
            if (readout_fallback) begin
                execution_path <= EXEC_DIGITAL;
                reason <= REASON_TILE_READOUT_FALLBACK | readout_reason;
                last_fallback_tile_id <= pending_tile_id;
                if (fallback_count != 16'hffff) begin
                    fallback_count <= fallback_count + 16'd1;
                end
                if (readout_reason == READOUT_REASON_RESIDUAL_HIGH && residual_fallback_count != 16'hffff) begin
                    residual_fallback_count <= residual_fallback_count + 16'd1;
                    if (residual_fallback_count >= 16'd1) begin
                        tile_health_action <= TILE_DISABLE;
                    end
                end
                if (readout_reason == READOUT_REASON_CALIBRATION_STALE && stale_fallback_count != 16'hffff) begin
                    stale_fallback_count <= stale_fallback_count + 16'd1;
                    if (tile_health_action != TILE_DISABLE) begin
                        tile_health_action <= TILE_RECALIBRATE;
                    end
                end
            end else if (readout_valid) begin
                execution_path <= EXEC_ANALOG_ACCEPTED;
                reason <= REASON_ANALOG_ACCEPTED;
                if (accepted_count != 16'hffff) begin
                    accepted_count <= accepted_count + 16'd1;
                end
            end else begin
                execution_path <= EXEC_DIGITAL;
                reason <= REASON_TILE_READOUT_FALLBACK;
            end
        end else if (sample_valid) begin
            if (placement == PLACE_DIGITAL) begin
                execution_path <= EXEC_DIGITAL;
                reason <= partition_reason;
            end else if (placement == PLACE_HYBRID) begin
                execution_path <= EXEC_HYBRID_REVIEW;
                reason <= REASON_HYBRID_REVIEW;
            end else begin
                analog_read_pending <= 1'b1;
                pending_tile_id <= tile_id;
            end
        end
    end
endmodule

analog-digital-chip-design-eda/labs/digital/aimc-control-plane-rtl/aimc_micro_tile_controller_tb.v
`timescale 1ns/1ps

module aimc_micro_tile_controller_tb;
    reg clk = 0;
    reg rst_n = 0;
    reg sample_valid = 0;
    reg [3:0] op_class = 4'd1;
    reg resident_weights = 1;
    reg [7:0] tile_id = 8'd0;
    reg tile_enabled = 1;
    reg [11:0] adc_code = 12'd160;
    reg signed [8:0] zero_code = 9'sd128;
    reg signed [8:0] gain_q6 = 9'sd64;
    reg signed [15:0] bias = 16'sd0;
    reg [7:0] estimated_state_error = 8'd60;
    reg [7:0] state_error_budget = 8'd100;
    reg [7:0] attention_flip_rate = 8'd5;
    reg [7:0] attention_flip_budget = 8'd15;
    reg [7:0] token_flip_rate = 8'd5;
    reg [7:0] token_flip_budget = 8'd15;
    reg [9:0] residual_abs = 10'd3;
    reg [9:0] residual_budget = 10'd20;
    reg [15:0] calibration_age = 16'd32;
    reg [7:0] weak_tiles = 8'd1;
    reg calibration_done = 0;
    reg probe_request = 0;
    reg probe_passed = 0;
    reg probe_failed = 0;
    wire signed [15:0] corrected_value;
    wire [1:0] execution_path;
    wire [3:0] reason;
    wire [7:0] last_fallback_tile_id;
    wire [15:0] fallback_count;
    wire [15:0] accepted_count;
    wire [15:0] residual_fallback_count;
    wire [15:0] stale_fallback_count;
    wire [1:0] tile_health_action;

    aimc_micro_tile_controller dut (
        .clk(clk),
        .rst_n(rst_n),
        .sample_valid(sample_valid),
        .op_class(op_class),
        .resident_weights(resident_weights),
        .tile_id(tile_id),
        .tile_enabled(tile_enabled),
        .adc_code(adc_code),
        .zero_code(zero_code),
        .gain_q6(gain_q6),
        .bias(bias),
        .estimated_state_error(estimated_state_error),
        .state_error_budget(state_error_budget),
        .attention_flip_rate(attention_flip_rate),
        .attention_flip_budget(attention_flip_budget),
        .token_flip_rate(token_flip_rate),
        .token_flip_budget(token_flip_budget),
        .residual_abs(residual_abs),
        .residual_budget(residual_budget),
        .calibration_age(calibration_age),
        .weak_tiles(weak_tiles),
        .calibration_done(calibration_done),
        .probe_request(probe_request),
        .probe_passed(probe_passed),
        .probe_failed(probe_failed),
        .corrected_value(corrected_value),
        .execution_path(execution_path),
        .reason(reason),
        .last_fallback_tile_id(last_fallback_tile_id),
        .fallback_count(fallback_count),
        .accepted_count(accepted_count),
        .residual_fallback_count(residual_fallback_count),
        .stale_fallback_count(stale_fallback_count),
        .tile_health_action(tile_health_action)
    );

    always #5 clk = ~clk;

    task run_case;
        input [160*8:1] name;
        input [3:0] in_op_class;
        input in_resident_weights;
        input [7:0] in_tile_id;
        input in_tile_enabled;
        input [9:0] in_residual_abs;
        input [15:0] in_calibration_age;
        input [1:0] expected_path;
        input [3:0] expected_reason;
        input [7:0] expected_last_fallback_tile_id;
        input [15:0] expected_fallback_count;
        input [15:0] expected_accepted_count;
        input [15:0] expected_residual_fallback_count;
        input [15:0] expected_stale_fallback_count;
        input [1:0] expected_tile_health_action;
        begin
            @(negedge clk);
            op_class = in_op_class;
            resident_weights = in_resident_weights;
            tile_id = in_tile_id;
            tile_enabled = in_tile_enabled;
            residual_abs = in_residual_abs;
            calibration_age = in_calibration_age;
            sample_valid = 1'b1;
            @(negedge clk);
            sample_valid = 1'b0;
            @(negedge clk);
            #1;
            $display("%0s,path=%0d,reason=%0d,value=%0d,last_fallback_tile=%0d,fallback_count=%0d,accepted_count=%0d,residual_fallback_count=%0d,stale_fallback_count=%0d,tile_health_action=%0d", name, execution_path, reason, corrected_value, last_fallback_tile_id, fallback_count, accepted_count, residual_fallback_count, stale_fallback_count, tile_health_action);
            if (
                execution_path !== expected_path ||
                reason !== expected_reason ||
                last_fallback_tile_id !== expected_last_fallback_tile_id ||
                fallback_count !== expected_fallback_count ||
                accepted_count !== expected_accepted_count ||
                residual_fallback_count !== expected_residual_fallback_count ||
                stale_fallback_count !== expected_stale_fallback_count ||
                tile_health_action !== expected_tile_health_action
            ) begin
                $display("FAIL %0s expected_path=%0d expected_reason=%0d expected_last_fallback_tile=%0d expected_fallback_count=%0d expected_accepted_count=%0d expected_residual_fallback_count=%0d expected_stale_fallback_count=%0d expected_tile_health_action=%0d", name, expected_path, expected_reason, expected_last_fallback_tile_id, expected_fallback_count, expected_accepted_count, expected_residual_fallback_count, expected_stale_fallback_count, expected_tile_health_action);
                $finish;
            end
        end
    endtask

    task run_control_case;
        input [160*8:1] name;
        input in_calibration_done;
        input in_probe_request;
        input in_probe_passed;
        input in_probe_failed;
        input [1:0] expected_tile_health_action;
        begin
            @(negedge clk);
            sample_valid = 1'b0;
            calibration_done = in_calibration_done;
            probe_request = in_probe_request;
            probe_passed = in_probe_passed;
            probe_failed = in_probe_failed;
            @(negedge clk);
            calibration_done = 1'b0;
            probe_request = 1'b0;
            probe_passed = 1'b0;
            probe_failed = 1'b0;
            #1;
            $display("%0s,path=%0d,reason=%0d,value=%0d,last_fallback_tile=%0d,fallback_count=%0d,accepted_count=%0d,residual_fallback_count=%0d,stale_fallback_count=%0d,tile_health_action=%0d", name, execution_path, reason, corrected_value, last_fallback_tile_id, fallback_count, accepted_count, residual_fallback_count, stale_fallback_count, tile_health_action);
            if (tile_health_action !== expected_tile_health_action) begin
                $display("FAIL %0s expected_tile_health_action=%0d", name, expected_tile_health_action);
                $finish;
            end
        end
    endtask

    initial begin
        $dumpfile("aimc_micro_tile_controller.vcd");
        $dumpvars(0, aimc_micro_tile_controller_tb);

        repeat (2) @(negedge clk);
        rst_n = 1'b1;

`include "generated_micro_tile_cases.vh"

        run_control_case("maintenance_disabled_enters_probe", 1'b0, 1'b1, 1'b0, 1'b0, 2'd3);
        run_control_case("maintenance_probe_failed_disables", 1'b0, 1'b0, 1'b0, 1'b1, 2'd2);
        run_control_case("maintenance_disabled_enters_probe_again", 1'b0, 1'b1, 1'b0, 1'b0, 2'd3);
        run_control_case("maintenance_probe_passed_serves", 1'b0, 1'b0, 1'b1, 1'b0, 2'd0);
        run_case("post_probe_stale_recalibrates", 4'd1, 1'b1, 8'd19, 1'b1, 10'd3, 16'd2048, 2'd0, 4'd11, 8'd19, 16'd5, 16'd1, 16'd2, 16'd2, 2'd1);
        run_control_case("maintenance_calibration_done_serves", 1'b1, 1'b0, 1'b0, 1'b0, 2'd0);

        $display("PASS aimc_micro_tile_controller_tb");
        $finish;
    end
endmodule

analog-digital-chip-design-eda/labs/digital/aimc-control-plane-rtl/aimc_micro_tile_controller.vcd
$date
	Wed Sep  2 16:17:33 2026
$end
$version
	Icarus Verilog
$end
$timescale
	1ps
$end
$scope module aimc_micro_tile_controller_tb $end
$var wire 2 ! tile_health_action [1:0] $end
$var wire 16 " stale_fallback_count [15:0] $end
$var wire 16 # residual_fallback_count [15:0] $end
$var wire 4 $ reason [3:0] $end
$var wire 8 % last_fallback_tile_id [7:0] $end
$var wire 16 & fallback_count [15:0] $end
$var wire 2 ' execution_path [1:0] $end
$var wire 16 ( corrected_value [15:0] $end
$var wire 16 ) accepted_count [15:0] $end
$var reg 12 * adc_code [11:0] $end
$var reg 8 + attention_flip_budget [7:0] $end
$var reg 8 , attention_flip_rate [7:0] $end
$var reg 16 - bias [15:0] $end
$var reg 16 . calibration_age [15:0] $end
$var reg 1 / calibration_done $end
$var reg 1 0 clk $end
$var reg 8 1 estimated_state_error [7:0] $end
$var reg 9 2 gain_q6 [8:0] $end
$var reg 4 3 op_class [3:0] $end
$var reg 1 4 probe_failed $end
$var reg 1 5 probe_passed $end
$var reg 1 6 probe_request $end
$var reg 1 7 resident_weights $end
$var reg 10 8 residual_abs [9:0] $end
$var reg 10 9 residual_budget [9:0] $end
$var reg 1 : rst_n $end
$var reg 1 ; sample_valid $end
$var reg 8 < state_error_budget [7:0] $end
$var reg 1 = tile_enabled $end
$var reg 8 > tile_id [7:0] $end
$var reg 8 ? token_flip_budget [7:0] $end
$var reg 8 @ token_flip_rate [7:0] $end
$var reg 8 A weak_tiles [7:0] $end
$var reg 9 B zero_code [8:0] $end
$scope module dut $end
$var wire 12 C adc_code [11:0] $end
$var wire 8 D attention_flip_budget [7:0] $end
$var wire 8 E attention_flip_rate [7:0] $end
$var wire 16 F bias [15:0] $end
$var wire 16 G calibration_age [15:0] $end
$var wire 1 / calibration_done $end
$var wire 1 0 clk $end
$var wire 8 H estimated_state_error [7:0] $end
$var wire 9 I gain_q6 [8:0] $end
$var wire 4 J op_class [3:0] $end
$var wire 1 4 probe_failed $end
$var wire 1 5 probe_passed $end
$var wire 1 6 probe_request $end
$var wire 1 7 resident_weights $end
$var wire 10 K residual_abs [9:0] $end
$var wire 10 L residual_budget [9:0] $end
$var wire 1 : rst_n $end
$var wire 1 ; sample_valid $end
$var wire 8 M state_error_budget [7:0] $end
$var wire 1 = tile_enabled $end
$var wire 8 N tile_id [7:0] $end
$var wire 8 O token_flip_budget [7:0] $end
$var wire 8 P token_flip_rate [7:0] $end
$var wire 8 Q weak_tiles [7:0] $end
$var wire 9 R zero_code [8:0] $end
$var wire 1 S readout_valid $end
$var wire 4 T readout_reason [3:0] $end
$var wire 1 U readout_fallback $end
$var wire 2 V placement [1:0] $end
$var wire 4 W partition_reason [3:0] $end
$var wire 16 X corrected_value [15:0] $end
$var reg 16 Y accepted_count [15:0] $end
$var reg 1 Z analog_read_pending $end
$var reg 2 [ execution_path [1:0] $end
$var reg 16 \ fallback_count [15:0] $end
$var reg 8 ] last_fallback_tile_id [7:0] $end
$var reg 8 ^ pending_tile_id [7:0] $end
$var reg 4 _ reason [3:0] $end
$var reg 16 ` residual_fallback_count [15:0] $end
$var reg 16 a stale_fallback_count [15:0] $end
$var reg 2 b tile_health_action [1:0] $end
$scope module partition $end
$var wire 8 c attention_flip_budget [7:0] $end
$var wire 8 d attention_flip_rate [7:0] $end
$var wire 16 e calibration_age [15:0] $end
$var wire 1 f digital_only $end
$var wire 8 g estimated_state_error [7:0] $end
$var wire 1 h fixed_weight_op $end
$var wire 1 i hybrid_candidate $end
$var wire 4 j op_class [3:0] $end
$var wire 1 7 resident_weights $end
$var wire 1 k stale_weak_tiles $end
$var wire 8 l state_error_budget [7:0] $end
$var wire 8 m token_flip_budget [7:0] $end
$var wire 8 n token_flip_rate [7:0] $end
$var wire 8 o weak_tiles [7:0] $end
$var reg 2 p placement [1:0] $end
$var reg 4 q reason [3:0] $end
$upscope $end
$scope module readout $end
$var wire 12 r adc_code [11:0] $end
$var wire 16 s bias [15:0] $end
$var wire 16 t calibration_age [15:0] $end
$var wire 1 0 clk $end
$var wire 9 u gain_q6 [8:0] $end
$var wire 10 v residual_abs [9:0] $end
$var wire 10 w residual_budget [9:0] $end
$var wire 1 : rst_n $end
$var wire 1 x sample_valid $end
$var wire 1 y should_fallback $end
$var wire 1 = tile_enabled $end
$var wire 9 z zero_code [8:0] $end
$var wire 26 { scaled [25:0] $end
$var wire 1 | saturated_low $end
$var wire 1 } saturated_high $end
$var wire 1 ~ residual_high $end
$var wire 26 !" corrected_wide [25:0] $end
$var wire 16 "" centered_adc [15:0] $end
$var wire 1 #" calibration_stale $end
$var reg 16 $" corrected_value [15:0] $end
$var reg 1 U fallback $end
$var reg 1 S output_valid $end
$var reg 4 %" reason [3:0] $end
$upscope $end
$upscope $end
$scope task run_case $end
$var reg 16 &" expected_accepted_count [15:0] $end
$var reg 16 '" expected_fallback_count [15:0] $end
$var reg 8 (" expected_last_fallback_tile_id [7:0] $end
$var reg 2 )" expected_path [1:0] $end
$var reg 4 *" expected_reason [3:0] $end
$var reg 16 +" expected_residual_fallback_count [15:0] $end
$var reg 16 ," expected_stale_fallback_count [15:0] $end
$var reg 2 -" expected_tile_health_action [1:0] $end
$var reg 16 ." in_calibration_age [15:0] $end
$var reg 4 /" in_op_class [3:0] $end
$var reg 1 0" in_resident_weights $end
$var reg 10 1" in_residual_abs [9:0] $end
$var reg 1 2" in_tile_enabled $end
$var reg 8 3" in_tile_id [7:0] $end
$var reg 1280 4" name [1280:1] $end
$upscope $end
$scope task run_control_case $end
$var reg 2 5" expected_tile_health_action [1:0] $end
$var reg 1 6" in_calibration_done $end
$var reg 1 7" in_probe_failed $end
$var reg 1 8" in_probe_passed $end
$var reg 1 9" in_probe_request $end
$var reg 1280 :" name [1280:1] $end
$upscope $end
$upscope $end
$enddefinitions $end
#0
$dumpvars
bx :"
x9"
x8"
x7"
x6"
bx 5"
bx 4"
bx 3"
x2"
bx 1"
x0"
bx /"
bx ."
bx -"
bx ,"
bx +"
bx *"
bx )"
bx ("
bx '"
bx &"
b0 %"
b0 $"
0#"
b100000 ""
b100000 !"
0~
0}
0|
b100000000000 {
b10000000 z
0y
0x
b10100 w
b11 v
b1000000 u
b100000 t
b0 s
b10100000 r
b1 q
b1 p
b1 o
b101 n
b1111 m
b1100100 l
0k
b1 j
0i
1h
b111100 g
0f
b100000 e
b101 d
b1111 c
b0 b
b0 a
b0 `
b0 _
b0 ^
b0 ]
b0 \
b0 [
0Z
b0 Y
b0 X
b1 W
b1 V
0U
b0 T
0S
b10000000 R
b1 Q
b101 P
b1111 O
b0 N
b1100100 M
b10100 L
b11 K
b1 J
b1000000 I
b111100 H
b100000 G
b0 F
b101 E
b1111 D
b10100000 C
b10000000 B
b1 A
b101 @
b1111 ?
b0 >
1=
b1100100 <
0;
0:
b10100 9
b11 8
17
06
05
04
b1 3
b1000000 2
b111100 1
00
0/
b100000 .
b0 -
b101 ,
b1111 +
b10100000 *
b0 )
b0 (
b0 '
b0 &
b0 %
b0 $
b0 #
b0 "
b0 !
$end
#5000
10
#10000
00
#15000
10
#20000
b0 -"
b0 ,"
b0 +"
b1 &"
b0 '"
b0 ("
b1 *"
b1 )"
b100000 ."
b11 1"
12"
b1011 3"
10"
b1 /"
b11100010110101101110110010111110110000101101110011000010110110001101111011001110101111101110010011001010110000101100100011011110111010101110100010111110110000101100011011000110110010101110000011101000110010101100100 4"
1:
00
#25000
10
#30000
1x
1;
b1011 >
b1011 N
00
#35000
b100000 (
b100000 X
b100000 $"
1S
b1011 ^
1Z
10
#40000
0x
0;
00
#45000
b1 )
b1 Y
b1 $
b1 _
b1 '
b1 [
0Z
0S
10
#50000
00
#51000
b1 +"
b1 '"
b1100 ("
b1010 *"
b0 )"
b101000 1"
b1100 3"
b1110001011010110111011001011111011100100110010101110011011010010110010001110101011000010110110001011111011001100110111101110010011000110110010101110011010111110110011001100001011011000110110001100010011000010110001101101011 4"
#55000
10
#60000
1y
1x
1;
1~
b101000 8
b101000 K
b101000 v
b1100 >
b1100 N
00
#65000
b1100 ^
1Z
b10 T
b10 %"
1U
10
#70000
0x
0;
00
#75000
b0 T
b0 %"
0U
b1 #
b1 `
b1 &
b1 \
b1100 %
b1100 ]
b1010 $
b1010 _
b0 '
b0 [
0Z
10
#80000
00
#81000
b1 -"
b1 ,"
b10 '"
b10001 ("
b1011 *"
b100000000000 ."
b11 1"
b10001 3"
b11100010110101101110110010111110111001101110100011000010110110001100101010111110110001101100001011011000110100101100010011100100110000101110100011010010110111101101110010111110110011001100001011011000110110001100010011000010110001101101011 4"
#85000
10
#90000
1x
1;
1#"
b100000000000 .
b100000000000 G
b100000000000 e
b100000000000 t
0~
b11 8
b11 K
b11 v
b10001 >
b10001 N
00
#95000
b11 T
b11 %"
1U
b10001 ^
1Z
10
#100000
0x
0;
00
#105000
b1 !
b1 b
b1 "
b1 a
b10 &
b10 \
b10001 %
b10001 ]
b1011 $
b1011 _
0Z
b0 T
b0 %"
0U
10
#110000
00
#111000
b11 '"
b1101 ("
b1001 *"
b100000 ."
02"
b1101 3"
b111000101101011011101100101111101100100011010010111001101100001011000100110110001100101011001000101111101110100011010010110110001100101010111110110011001100001011011000110110001100010011000010110001101101011 4"
#115000
10
#120000
1x
1;
0#"
b100000 .
b100000 G
b100000 e
b100000 t
0=
b1101 >
b1101 N
00
#125000
b1101 ^
1Z
b1 T
b1 %"
1U
10
#130000
0x
0;
00
#135000
b0 T
b0 %"
0U
b11 &
b11 \
b1101 %
b1101 ]
b1001 $
b1001 _
0Z
10
#140000
00
#141000
b10 *"
b10 )"
12"
b1110 3"
b10 /"
b110000101110100011101000110010101101110011101000110100101101111011011100101111101110011011000110110111101110010011001010101111101101000011110010110001001110010011010010110010001011111011100100110010101110110011010010110010101110111 4"
#145000
10
#150000
0y
1i
0h
0x
b10 W
b10 q
b10 V
b10 p
1;
1=
b1110 >
b1110 N
b10 3
b10 J
b10 j
00
