analog-digital-chip-design-eda/labs/eda/aimc-micro-tile-controller-openlane-prep/src/aimc_operation_partition.v
module aimc_operation_partition (
    input wire [3:0] op_class,
    input wire resident_weights,
    input wire [7:0] estimated_state_error,
    input wire [7:0] state_error_budget,
    input wire [7:0] attention_flip_rate,
    input wire [7:0] attention_flip_budget,
    input wire [7:0] token_flip_rate,
    input wire [7:0] token_flip_budget,
    input wire [15:0] calibration_age,
    input wire [7:0] weak_tiles,
    output reg [1:0] placement,
    output reg [3:0] reason
);
    localparam OP_EMBEDDING = 4'd0;
    localparam OP_QKV = 4'd1;
    localparam OP_ATTENTION_SCORE = 4'd2;
    localparam OP_MASK = 4'd3;
    localparam OP_SOFTMAX = 4'd4;
    localparam OP_VALUE_MIX = 4'd5;
    localparam OP_OUT_PROJ = 4'd6;
    localparam OP_MLP = 4'd7;
    localparam OP_RESIDUAL = 4'd8;
    localparam OP_NORM = 4'd9;
    localparam OP_KV_CACHE = 4'd10;
    localparam OP_LOGITS = 4'd11;
    localparam OP_SAMPLING = 4'd12;
    localparam OP_ADAPTER = 4'd13;

    localparam PLACE_DIGITAL = 2'd0;
    localparam PLACE_ANALOG = 2'd1;
    localparam PLACE_HYBRID = 2'd2;

    localparam REASON_DIGITAL_RULE = 4'd0;
    localparam REASON_FIXED_WEIGHT_ANALOG = 4'd1;
    localparam REASON_HYBRID_NEEDS_EVIDENCE = 4'd2;
    localparam REASON_MISSING_WEIGHTS = 4'd3;
    localparam REASON_STATE_ERROR_HIGH = 4'd4;
    localparam REASON_ATTENTION_SELECTION_HIGH = 4'd5;
    localparam REASON_TOKEN_CHOICE_HIGH = 4'd6;
    localparam REASON_STALE_WEAK_TILES = 4'd7;
    localparam REASON_UNKNOWN_OP = 4'd15;

    wire stale_weak_tiles = (calibration_age >= 16'd1024) && (weak_tiles >= 8'd4);
    wire fixed_weight_op = (op_class == OP_QKV) || (op_class == OP_OUT_PROJ) || (op_class == OP_MLP);
    wire hybrid_candidate = (op_class == OP_ATTENTION_SCORE) || (op_class == OP_VALUE_MIX) || (op_class == OP_LOGITS) || (op_class == OP_ADAPTER);
    wire digital_only = (op_class == OP_EMBEDDING) || (op_class == OP_MASK) || (op_class == OP_SOFTMAX) ||
        (op_class == OP_RESIDUAL) || (op_class == OP_NORM) || (op_class == OP_KV_CACHE) || (op_class == OP_SAMPLING);

    always @* begin
        placement = PLACE_DIGITAL;
        reason = REASON_UNKNOWN_OP;

        if (digital_only) begin
            placement = PLACE_DIGITAL;
            reason = REASON_DIGITAL_RULE;
        end else if (!resident_weights && (fixed_weight_op || hybrid_candidate)) begin
            placement = PLACE_DIGITAL;
            reason = REASON_MISSING_WEIGHTS;
        end else if (estimated_state_error > state_error_budget) begin
            placement = PLACE_DIGITAL;
            reason = REASON_STATE_ERROR_HIGH;
        end else if (stale_weak_tiles) begin
            placement = PLACE_DIGITAL;
            reason = REASON_STALE_WEAK_TILES;
        end else if ((op_class == OP_ATTENTION_SCORE || op_class == OP_VALUE_MIX) && (attention_flip_rate > attention_flip_budget)) begin
            placement = PLACE_DIGITAL;
            reason = REASON_ATTENTION_SELECTION_HIGH;
        end else if (op_class == OP_LOGITS && (token_flip_rate > token_flip_budget)) begin
            placement = PLACE_DIGITAL;
            reason = REASON_TOKEN_CHOICE_HIGH;
        end else if (fixed_weight_op) begin
            placement = PLACE_ANALOG;
            reason = REASON_FIXED_WEIGHT_ANALOG;
        end else if (hybrid_candidate) begin
            placement = PLACE_HYBRID;
            reason = REASON_HYBRID_NEEDS_EVIDENCE;
        end else begin
            placement = PLACE_DIGITAL;
            reason = REASON_UNKNOWN_OP;
        end
    end
endmodule

analog-digital-chip-design-eda/labs/digital/aimc-control-plane-rtl/aimc_operation_partition_tb.v
`timescale 1ns/1ps

module aimc_operation_partition_tb;
    reg [3:0] op_class = 0;
    reg resident_weights = 1;
    reg [7:0] estimated_state_error = 8'd60;
    reg [7:0] state_error_budget = 8'd100;
    reg [7:0] attention_flip_rate = 8'd5;
    reg [7:0] attention_flip_budget = 8'd15;
    reg [7:0] token_flip_rate = 8'd5;
    reg [7:0] token_flip_budget = 8'd15;
    reg [15:0] calibration_age = 16'd128;
    reg [7:0] weak_tiles = 8'd1;
    wire [1:0] placement;
    wire [3:0] reason;

    aimc_operation_partition dut (
        .op_class(op_class),
        .resident_weights(resident_weights),
        .estimated_state_error(estimated_state_error),
        .state_error_budget(state_error_budget),
        .attention_flip_rate(attention_flip_rate),
        .attention_flip_budget(attention_flip_budget),
        .token_flip_rate(token_flip_rate),
        .token_flip_budget(token_flip_budget),
        .calibration_age(calibration_age),
        .weak_tiles(weak_tiles),
        .placement(placement),
        .reason(reason)
    );

    task run_case;
        input [160*8:1] name;
        input [3:0] in_op_class;
        input in_resident_weights;
        input [7:0] in_estimated_state_error;
        input [7:0] in_attention_flip_rate;
        input [7:0] in_token_flip_rate;
        input [15:0] in_calibration_age;
        input [7:0] in_weak_tiles;
        input [1:0] expected_placement;
        input [3:0] expected_reason;
        begin
            op_class = in_op_class;
            resident_weights = in_resident_weights;
            estimated_state_error = in_estimated_state_error;
            attention_flip_rate = in_attention_flip_rate;
            token_flip_rate = in_token_flip_rate;
            calibration_age = in_calibration_age;
            weak_tiles = in_weak_tiles;
            #1;
            $display("%0s,placement=%0d,reason=%0d,expected_placement=%0d,expected_reason=%0d",
                name, placement, reason, expected_placement, expected_reason);
            if (placement !== expected_placement || reason !== expected_reason) begin
                $display("FAIL %0s", name);
                $finish;
            end
        end
    endtask

    initial begin
        $dumpfile("aimc_operation_partition.vcd");
        $dumpvars(0, aimc_operation_partition_tb);

        run_case("embedding_is_digital", 4'd0, 1'b1, 8'd60, 8'd5, 8'd5, 16'd128, 8'd1, 2'd0, 4'd0);
        run_case("qkv_fixed_weight_analog", 4'd1, 1'b1, 8'd60, 8'd5, 8'd5, 16'd128, 8'd1, 2'd1, 4'd1);
        run_case("mlp_fixed_weight_analog", 4'd7, 1'b1, 8'd60, 8'd5, 8'd5, 16'd128, 8'd1, 2'd1, 4'd1);
        run_case("attention_score_hybrid", 4'd2, 1'b1, 8'd60, 8'd5, 8'd5, 16'd128, 8'd1, 2'd2, 4'd2);
        run_case("attention_selection_fallback", 4'd2, 1'b1, 8'd60, 8'd28, 8'd5, 16'd128, 8'd1, 2'd0, 4'd5);
        run_case("logits_hybrid", 4'd11, 1'b1, 8'd60, 8'd5, 8'd5, 16'd128, 8'd1, 2'd2, 4'd2);
        run_case("logits_token_fallback", 4'd11, 1'b1, 8'd60, 8'd5, 8'd22, 16'd128, 8'd1, 2'd0, 4'd6);
        run_case("kv_cache_is_digital", 4'd10, 1'b1, 8'd60, 8'd5, 8'd5, 16'd128, 8'd1, 2'd0, 4'd0);
        run_case("state_error_fallback", 4'd1, 1'b1, 8'd120, 8'd5, 8'd5, 16'd128, 8'd1, 2'd0, 4'd4);
        run_case("stale_weak_fallback", 4'd7, 1'b1, 8'd60, 8'd5, 8'd5, 16'd2048, 8'd8, 2'd0, 4'd7);
        run_case("missing_weights_fallback", 4'd1, 1'b0, 8'd60, 8'd5, 8'd5, 16'd128, 8'd1, 2'd0, 4'd3);

        $display("PASS aimc_operation_partition_tb");
        $finish;
    end
endmodule

analog-digital-chip-design-eda/labs/digital/aimc-control-plane-rtl/aimc_operation_partition.vcd
$date
	Sat Aug 29 05:37:55 2026
$end
$version
	Icarus Verilog
$end
$timescale
	1ps
$end
$scope module aimc_operation_partition_tb $end
$var wire 4 ! reason [3:0] $end
$var wire 2 " placement [1:0] $end
$var reg 8 # attention_flip_budget [7:0] $end
$var reg 8 $ attention_flip_rate [7:0] $end
$var reg 16 % calibration_age [15:0] $end
$var reg 8 & estimated_state_error [7:0] $end
$var reg 4 ' op_class [3:0] $end
$var reg 1 ( resident_weights $end
$var reg 8 ) state_error_budget [7:0] $end
$var reg 8 * token_flip_budget [7:0] $end
$var reg 8 + token_flip_rate [7:0] $end
$var reg 8 , weak_tiles [7:0] $end
$scope module dut $end
$var wire 8 - attention_flip_budget [7:0] $end
$var wire 8 . attention_flip_rate [7:0] $end
$var wire 16 / calibration_age [15:0] $end
$var wire 1 0 digital_only $end
$var wire 8 1 estimated_state_error [7:0] $end
$var wire 1 2 fixed_weight_op $end
$var wire 1 3 hybrid_candidate $end
$var wire 4 4 op_class [3:0] $end
$var wire 1 ( resident_weights $end
$var wire 1 5 stale_weak_tiles $end
$var wire 8 6 state_error_budget [7:0] $end
$var wire 8 7 token_flip_budget [7:0] $end
$var wire 8 8 token_flip_rate [7:0] $end
$var wire 8 9 weak_tiles [7:0] $end
$var reg 2 : placement [1:0] $end
$var reg 4 ; reason [3:0] $end
$upscope $end
$scope task run_case $end
$var reg 2 < expected_placement [1:0] $end
$var reg 4 = expected_reason [3:0] $end
$var reg 8 > in_attention_flip_rate [7:0] $end
$var reg 16 ? in_calibration_age [15:0] $end
$var reg 8 @ in_estimated_state_error [7:0] $end
$var reg 4 A in_op_class [3:0] $end
$var reg 1 B in_resident_weights $end
$var reg 8 C in_token_flip_rate [7:0] $end
$var reg 8 D in_weak_tiles [7:0] $end
$var reg 1280 E name [1280:1] $end
$upscope $end
$upscope $end
$enddefinitions $end
#0
$dumpvars
b110010101101101011000100110010101100100011001000110100101101110011001110101111101101001011100110101111101100100011010010110011101101001011101000110000101101100 E
b1 D
b101 C
1B
b0 A
b111100 @
b10000000 ?
b101 >
b0 =
b0 <
b0 ;
b0 :
b1 9
b101 8
b1111 7
b1100100 6
05
b0 4
03
02
b111100 1
10
b10000000 /
b101 .
b1111 -
b1 ,
b101 +
b1111 *
b1100100 )
1(
b0 '
b111100 &
b10000000 %
b101 $
b1111 #
b0 "
b0 !
$end
#1000
b1 "
b1 :
00
12
b1 !
b1 ;
b1 '
b1 4
b1 =
b1 <
b1 A
b111000101101011011101100101111101100110011010010111100001100101011001000101111101110111011001010110100101100111011010000111010001011111011000010110111001100001011011000110111101100111 E
#2000
b1 !
b1 ;
b1 "
b1 :
b111 '
b111 4
b111 A
b110110101101100011100000101111101100110011010010111100001100101011001000101111101110111011001010110100101100111011010000111010001011111011000010110111001100001011011000110111101100111 E
#3000
13
b10 !
b10 ;
b10 "
b10 :
02
b10 '
b10 4
b10 =
b10 <
b10 A
b1100001011101000111010001100101011011100111010001101001011011110110111001011111011100110110001101101111011100100110010101011111011010000111100101100010011100100110100101100100 E
#4000
b101 !
b101 ;
b0 "
b0 :
b11100 $
b11100 .
b101 =
b0 <
b11100 >
b1100001011101000111010001100101011011100111010001101001011011110110111001011111011100110110010101101100011001010110001101110100011010010110111101101110010111110110011001100001011011000110110001100010011000010110001101101011 E
#5000
b10 "
b10 :
b10 !
b10 ;
b101 $
b101 .
b1011 '
b1011 4
b10 =
b10 <
b101 >
b1011 A
b1101100011011110110011101101001011101000111001101011111011010000111100101100010011100100110100101100100 E
#6000
b110 !
b110 ;
b0 "
b0 :
b10110 +
b10110 8
b110 =
b0 <
b10110 C
b11011000110111101100111011010010111010001110011010111110111010001101111011010110110010101101110010111110110011001100001011011000110110001100010011000010110001101101011 E
#7000
03
10
b0 "
b0 :
b0 !
b0 ;
b101 +
b101 8
b1010 '
b1010 4
b0 =
b101 C
b1010 A
b1101011011101100101111101100011011000010110001101101000011001010101111101101001011100110101111101100100011010010110011101101001011101000110000101101100 E
#8000
12
00
b100 !
b100 ;
b1111000 &
b1111000 1
b1 '
b1 4
b100 =
b1111000 @
b1 A
b111001101110100011000010111010001100101010111110110010101110010011100100110111101110010010111110110011001100001011011000110110001100010011000010110001101101011 E
#9000
15
b0 "
b0 :
b111 !
b111 ;
b1000 ,
b1000 9
b100000000000 %
b100000000000 /
b111100 &
b111100 1
b111 '
b111 4
b111 =
b1000 D
b100000000000 ?
b111100 @
b111 A
b1110011011101000110000101101100011001010101111101110111011001010110000101101011010111110110011001100001011011000110110001100010011000010110001101101011 E
#10000
05
b11 !
b11 ;
12
b1 ,
b1 9
b10000000 %
b10000000 /
0(
b1 '
b1 4
b11 =
b1 D
b10000000 ?
0B
b1 A
b11011010110100101110011011100110110100101101110011001110101111101110111011001010110100101100111011010000111010001110011010111110110011001100001011011000110110001100010011000010110001101101011 E
